treeplot/__init__.py
treeplot/examples.py
treeplot/treeplot.py
treeplot/RESOURCES/__init__.py
treeplot-0.2.0.dist-info/LICENSE
treeplot-0.2.0.dist-info/METADATA
treeplot-0.2.0.dist-info/WHEEL
treeplot-0.2.0.dist-info/top_level.txt
treeplot-0.2.0.dist-info/RECORD
