Metadata-Version: 2.1
Name: treeplot
Version: 0.2.0
Summary: Python package treeplot vizualizes a tree based on a randomforest or xgboost model.
Home-page: https://erdogant.github.io//treeplot
Download-URL: https://github.com/erdogant/treeplot/archive/0.2.0.tar.gz
Author: Erdogan Taskesen
Author-email: erdogant@gmail.com
Classifier: Programming Language :: Python :: 3
Classifier: License :: OSI Approved :: MIT License
Classifier: Operating System :: OS Independent
Requires-Python: >=3
License-File: LICENSE
Requires-Dist: scikit-learn
Requires-Dist: numpy
Requires-Dist: graphviz>=0.20.1
Requires-Dist: matplotlib
Requires-Dist: funcsigs
Requires-Dist: setgraphviz
